LICENSE.txt
README.md
setup.cfg
setup.py
coala/__init__.py
coala/test.py
coala_fl.egg-info/PKG-INFO
coala_fl.egg-info/SOURCES.txt
coala_fl.egg-info/dependency_links.txt
coala_fl.egg-info/requires.txt
coala_fl.egg-info/top_level.txt