Metadata-Version: 2.1
Name: coala-fl
Version: 0.0.1
Summary: Federated learning Platform
Home-page: https://github.com/
Download-URL: https://github.com/weiming-sony/coala-pypi/archive/refs/tags/v0.0.1.tar.gz
Author: YOUR NAME
Author-email: your.email@domain.com
License: MIT
Keywords: Federated Learning
Classifier: Development Status :: 3 - Alpha
Classifier: Intended Audience :: Developers
Classifier: Topic :: Software Development :: Build Tools
Classifier: License :: OSI Approved :: MIT License
Classifier: Programming Language :: Python :: 3.8
License-File: LICENSE.txt
Requires-Dist: numpy
